{ 
"wallpapers": 
	[
		{
			"author": "Someone",
			"url": "http://i.imgur.com/oIhJ6ic.jpg",
			"name": "Wallpaper 01",
			"resolution": "1024x768"
		},
		{
			"author": "Someone",
			"url": "http://i.imgur.com/lQVjoy7.jpg",
			"name": "Wallpaper 02",
			"resolution": "2560x1440"

		},
		{
			"author": "Someone",
			"url": "http://i.imgur.com/0RGW6OY.jpg",
			"name": "Wallpaper 03",
			"resolution": "3940x2160"
		},
		{
			"author": "Someone",
			"url": "http://i.imgur.com/wGjj0e7.jpg",
			"name": "Wallpaper 04",
			"resolution": "1024x768"
		},
		{
			"author": "Someone",
			"url": "http://i.imgur.com/HVc6ANO.jpg",
			"name": "Wallpaper 05",
			"resolution": "2560x1440"

		},
		{
			"author": "Someone",
			"url": "http://i.imgur.com/kqRAChW.jpg",
			"name": "Wallpaper 06",
			"resolution": "3940x2160"
		}
	]
}
